labquant/__init__.py
labquant/candlestick.py
labquant/datetimeaxis.py
labquant/labquant.py
labquant/multlines.py
labquant/simulations.py
labquant/utils.py
labquant-0.1.2.dist-info/METADATA
labquant-0.1.2.dist-info/WHEEL
labquant-0.1.2.dist-info/RECORD
