Metadata-Version: 2.1
Name: LabQuant
Version: 0.1.2
Summary: LabQuant is a tool to support the development and evaluation of algo-strategies in quantitative finance.
Home-page: https://github.com/fab2112/LabQuant
License: MIT
Author: Fabrício Siqueira
Requires-Python: >=3.11,<4.0
Classifier: License :: OSI Approved :: MIT License
Classifier: Programming Language :: Python :: 3
Classifier: Programming Language :: Python :: 3.11
Classifier: Programming Language :: Python :: 3.12
Requires-Dist: PyQt5 (==5.15.10)
Requires-Dist: PyQt5-Qt5 (==5.15.2)
Requires-Dist: PyQt5-sip (==12.13.0)
Requires-Dist: colorama (==0.4.6)
Requires-Dist: numpy (==1.26.4)
Requires-Dist: pandas (==2.2.2)
Requires-Dist: pyqtgraph (==0.13.7)
Requires-Dist: scikit-learn (==1.4.2)
Requires-Dist: scikit-optimize (==0.10.2)
